nbr/__init__.py
nbr/api.py
nbr/exceptions.py
nbr/kernel.py
nbr/notebook.py
nbr/runner.py
nbr/schemas/__init__.py
nbr/schemas/message.py
nbr/schemas/result.py
nbr/schemas/session.py
nbr/utils/__init__.py
nbr/utils/client.py
nbr/utils/contents.py
nbr/utils/message.py
nbr/utils/session.py
nbr/utils/websocket.py
nbr-1.0.0b0.dist-info/LICENSE
nbr-1.0.0b0.dist-info/WHEEL
nbr-1.0.0b0.dist-info/METADATA
nbr-1.0.0b0.dist-info/RECORD
