Metadata-Version: 2.1
Name: nbr
Version: 1.0.0b0
Summary: Jupyter notebooks runner
Home-page: https://github.com/zhivykh/nbr
Keywords: jupyter,jupyter-notebook
Author: Nick Zhivykh
Requires-Python: >=3.10,<4.0
Classifier: Programming Language :: Python :: 3
Classifier: Programming Language :: Python :: 3.10
Requires-Dist: httpx (>=0.22.0,<0.23.0)
Requires-Dist: nbformat (>=5.3.0,<6.0.0)
Requires-Dist: pydantic (>=1.9.0,<2.0.0)
Requires-Dist: websockets (>=10.2,<11.0)
Project-URL: Repository, https://github.com/zhivykh/nbr
